Metadata-Version: 2.1
Name: Supbotai
Version: 0.2.2
Summary: Supbot is a customer service bot can be integrated with any website
Author: Supbot L.T.D
Author-email: yousef.gamal.2951@gmail.com
Classifier: Development Status :: 3 - Alpha
Classifier: Intended Audience :: Developers
Classifier: License :: OSI Approved :: MIT License
Classifier: Programming Language :: Python :: 3.6
Classifier: Programming Language :: Python :: 3.7
Classifier: Programming Language :: Python :: 3.8
Classifier: Programming Language :: Python :: 3.9
License-File: LICENSE.txt
